pybind11_cmake/FindCatch.cmake
pybind11_cmake/FindEigen3.cmake
pybind11_cmake/FindPythonLibsNew.cmake
pybind11_cmake/__init__.py
pybind11_cmake/check-style.sh
pybind11_cmake/libsize.py
pybind11_cmake/mkdoc.py
pybind11_cmake/pybind11Config.cmake
pybind11_cmake/pybind11Tools.cmake
pybind11_cmake-1.0.0.data/scripts/pybind11_new_project
pybind11_cmake-1.0.0.dist-info/LICENSE
pybind11_cmake-1.0.0.dist-info/METADATA
pybind11_cmake-1.0.0.dist-info/WHEEL
pybind11_cmake-1.0.0.dist-info/top_level.txt
pybind11_cmake-1.0.0.dist-info/RECORD
