Metadata-Version: 2.1
Name: pybind11-cmake
Version: 1.0.0
Summary: Straightforward boilerplate generation for pybind11 + cmake
Home-page: https://github.com/safijari/pybind11-cmake
Author: Jariullah Safi
Author-email: safijari@isu.edu
License: UNKNOWN
Keywords: C++11,Python bindings,CMake,boilerplate
Platform: UNKNOWN
Classifier: Development Status :: 5 - Production/Stable
Classifier: Intended Audience :: Developers
Classifier: Topic :: Software Development :: Libraries :: Python Modules
Classifier: Topic :: Utilities
Classifier: Programming Language :: C++
Classifier: Programming Language :: Python :: 2.7
Classifier: Programming Language :: Python :: 3
Classifier: Programming Language :: Python :: 3.2
Classifier: Programming Language :: Python :: 3.3
Classifier: Programming Language :: Python :: 3.4
Classifier: Programming Language :: Python :: 3.5
Classifier: Programming Language :: Python :: 3.6
Classifier: Programming Language :: Python :: 3.7
Classifier: License :: OSI Approved :: BSD License
Requires-Dist: pybind11 (<3,>=2)
Requires-Dist: argh
